CHANGELOG.md
LICENSE
MANIFEST.in
README.md
requirements.txt
setup.py
amplpyfinance/__init__.py
amplpyfinance/discrete_allocation.py
amplpyfinance.egg-info/PKG-INFO
amplpyfinance.egg-info/SOURCES.txt
amplpyfinance.egg-info/dependency_links.txt
amplpyfinance.egg-info/requires.txt
amplpyfinance.egg-info/top_level.txt
amplpyfinance/efficient_frontier/__init__.py
amplpyfinance/efficient_frontier/efficient_frontier.py
amplpyfinance/tests/TestBase.py
amplpyfinance/tests/__init__.py
amplpyfinance/tests/__main__.py
amplpyfinance/tests/test_discrete_allocation.py
amplpyfinance/tests/test_effiecient_frontier.py
amplpyfinance/tests/test_effiecient_frontier_models.py