Metadata-Version: 2.1
Name: amplpyfinance
Version: 0.0.0a2
Summary: Financial portfolio optimization with amplpy
Home-page: http://ampl.com/
Author: Filipe Brandão
Author-email: fdabrandao@gmail.com
Maintainer: Filipe Brandão
Maintainer-email: fdabrandao@ampl.com
License: MIT
Download-URL: https://github.com/ampl/amplpy/tree/master/amplpyfinance
Platform: any
Classifier: Development Status :: 4 - Beta
Classifier: Environment :: Console
Classifier: Topic :: Software Development
Classifier: Topic :: Scientific/Engineering
Classifier: Intended Audience :: Developers
Classifier: Intended Audience :: Science/Research
Classifier: License :: OSI Approved :: BSD License
Classifier: Operating System :: POSIX
Classifier: Operating System :: Unix
Classifier: Operating System :: MacOS
Classifier: Operating System :: Microsoft :: Windows
Classifier: Programming Language :: Python
Classifier: Programming Language :: Python :: 3
Classifier: Programming Language :: Python :: Implementation :: CPython
License-File: LICENSE
